pwncli/__init__.py
pwncli/cli.py
pwncli/commands/__init__.py
pwncli/commands/cmd_config.py
pwncli/commands/cmd_debug.py
pwncli/commands/cmd_example.py
pwncli/commands/cmd_gadget.py
pwncli/commands/cmd_initial.py
pwncli/commands/cmd_listen.py
pwncli/commands/cmd_misc.py
pwncli/commands/cmd_patchelf.py
pwncli/commands/cmd_qemu.py
pwncli/commands/cmd_remote.py
pwncli/commands/cmd_template.py
pwncli/commands/cmd_tmux.py
pwncli/commands/cmd_update.py
pwncli/conf/config_data.conf
pwncli/utils/__init__.py
pwncli/utils/bruteforce.py
pwncli/utils/cli_decorates.py
pwncli/utils/cli_misc.py
pwncli/utils/config.py
pwncli/utils/decorates.py
pwncli/utils/exceptions.py
pwncli/utils/gadgetbox.py
pwncli/utils/gdb_helper.py
pwncli/utils/io_file.py
pwncli/utils/libcbox.py
pwncli/utils/misc.py
pwncli/utils/pipes.py
pwncli/utils/shellcode.py
pwncli/utils/syscall_num.py
pwncli-1.6.dist-info/LICENSE
pwncli-1.6.dist-info/METADATA
pwncli-1.6.dist-info/WHEEL
pwncli-1.6.dist-info/entry_points.txt
pwncli-1.6.dist-info/top_level.txt
pwncli-1.6.dist-info/RECORD
