Metadata-Version: 2.1
Name: pwncli
Version: 1.6
Summary: pwncli, do pwn quickly.
Home-page: https://github.com/RoderickChan/pwncli
Author: roderick chan
Author-email: roderickchan@foxmail.com
Classifier: Programming Language :: Python :: 3
Classifier: License :: OSI Approved :: MIT License
License-File: LICENSE
Requires-Dist: click
Requires-Dist: pwntools
